{
    "station_list": [
        {
            "arrive_day_str": "当日到达",
            "station_name": "呼和浩特东",
            "train_class_name": "快速",
            "is_start": "Y",
            "service_type": "1",
            "end_station_name": "赤峰南",
            "arrive_time": "----",
            "start_station_name": "呼和浩特东",
            "station_train_code": "K4696",
            "arrive_day_diff": "0",
            "start_time": "21:50",
            "station_no": "01",
            "wz_num": "--",
            "running_time": "00:00"
        },
        {
            "arrive_day_str": "当日到达",
            "arrive_time": "23:15",
            "station_train_code": "K4697",
            "station_name": "集宁南",
            "arrive_day_diff": "0",
            "OT": [],
            "start_time": "23:30",
            "wz_num": "--",
            "station_no": "02",
            "running_time": "01:25"
        },
        {
            "arrive_day_str": "次日到达",
            "arrive_time": "00:40",
            "station_train_code": "K4697",
            "station_name": "商都",
            "arrive_day_diff": "1",
            "OT": [],
            "start_time": "00:42",
            "wz_num": "--",
            "station_no": "03",
            "running_time": "02:50"
        },
        {
            "arrive_day_str": "次日到达",
            "arrive_time": "01:25",
            "station_train_code": "K4697",
            "station_name": "化德",
            "arrive_day_diff": "1",
            "OT": [],
            "start_time": "01:27",
            "wz_num": "--",
            "station_no": "04",
            "running_time": "03:35"
        },
        {
            "arrive_day_str": "次日到达",
            "arrive_time": "02:41",
            "station_train_code": "K4697",
            "station_name": "正镶白旗",
            "arrive_day_diff": "1",
            "OT": [],
            "start_time": "02:47",
            "wz_num": "--",
            "station_no": "05",
            "running_time": "04:51"
        },
        {
            "arrive_day_str": "次日到达",
            "arrive_time": "03:52",
            "station_train_code": "K4697",
            "station_name": "桑根达来",
            "arrive_day_diff": "1",
            "OT": [],
            "start_time": "03:58",
            "wz_num": "--",
            "station_no": "06",
            "running_time": "06:02"
        },
        {
            "arrive_day_str": "次日到达",
            "arrive_time": "07:17",
            "station_train_code": "K4697",
            "station_name": "林西",
            "arrive_day_diff": "1",
            "OT": [],
            "start_time": "07:19",
            "wz_num": "--",
            "station_no": "07",
            "running_time": "09:27"
        },
        {
            "arrive_day_str": "次日到达",
            "arrive_time": "08:05",
            "station_train_code": "K4697",
            "station_name": "大板",
            "arrive_day_diff": "1",
            "OT": [],
            "start_time": "08:17",
            "wz_num": "--",
            "station_no": "08",
            "running_time": "10:15"
        },
        {
            "arrive_day_str": "次日到达",
            "arrive_time": "12:08",
            "station_train_code": "K4697",
            "station_name": "赤峰南",
            "arrive_day_diff": "1",
            "OT": [],
            "start_time": "12:08",
            "wz_num": "--",
            "station_no": "09",
            "running_time": "14:18"
        }
    ],
    "station_names": [
        "呼和浩特东",
        "集宁南",
        "商都",
        "化德",
        "正镶白旗",
        "桑根达来",
        "林西",
        "大板",
        "赤峰南"
    ],
    "train_search_no": "33000K469603"
}